fileinspector.py
python_fileinspector-1.0.2.dist-info/DESCRIPTION.rst
python_fileinspector-1.0.2.dist-info/METADATA
python_fileinspector-1.0.2.dist-info/RECORD
python_fileinspector-1.0.2.dist-info/WHEEL
python_fileinspector-1.0.2.dist-info/metadata.json
python_fileinspector-1.0.2.dist-info/top_level.txt
