Metadata-Version: 2.0
Name: python-fileinspector
Version: 1.0.2
Summary: A module to determine file mimetypes
Home-page: https://github.com/dschreij/fileinspector
Author: Daniel Schreij
Author-email: dschreij@gmail.com
License: UNKNOWN
Platform: UNKNOWN
Classifier: Intended Audience :: Developers
Classifier: Topic :: Desktop Environment
Classifier: License :: OSI Approved :: GNU General Public License v3 (GPLv3)
Classifier: Programming Language :: Python :: 2
Classifier: Programming Language :: Python :: 3
